pywooscraper/__init__.py
pywooscraper/scraper.py
pywooscraper/utils.py
pywooscraper-0.1.1.dist-info/METADATA
pywooscraper-0.1.1.dist-info/WHEEL
pywooscraper-0.1.1.dist-info/top_level.txt
pywooscraper-0.1.1.dist-info/RECORD
